jload/__init__.py
jload-0.7.1.dist-info/licenses/LICENSE
jload-0.7.1.dist-info/METADATA
jload-0.7.1.dist-info/WHEEL
jload-0.7.1.dist-info/top_level.txt
jload-0.7.1.dist-info/RECORD
