Metadata-Version: 2.4
Name: jload
Version: 0.7.1
Summary: A simple utility to load JSON/JSONL files as lists of dictionaries, and save various data types to JSON/JSONL.
Author-email: Bohan Lyu <lyubh22@gmail.com>
License-Expression: MIT
Project-URL: Homepage, https://github.com/Imbernoulli/jload
Project-URL: Bug Reports, https://github.com/Imbernoulli/jload/issues
Project-URL: Source, https://github.com/Imbernoulli/jload/
Classifier: Programming Language :: Python :: 3
Classifier: Operating System :: OS Independent
Classifier: Topic :: Software Development :: Libraries :: Python Modules
Classifier: Topic :: Utilities
Classifier: Intended Audience :: Developers
Requires-Python: >=3.7
License-File: LICENSE
Dynamic: license-file
